LICENSE
README.md
setup.py
veloce/__init__.py
veloce/callback.py
veloce/environ.py
veloce/epochvisor.py
veloce/feature_column.py
veloce/inputs.py
veloce/loss_fn.py
veloce/preprocessing.py
veloce/train_fn.py
veloce/trainer.py
veloce/version.py
veloce.egg-info/PKG-INFO
veloce.egg-info/SOURCES.txt
veloce.egg-info/dependency_links.txt
veloce.egg-info/requires.txt
veloce.egg-info/top_level.txt
veloce/heterogeneous/__init__.py
veloce/heterogeneous/ps.py
veloce/heterogeneous/strategy.py
veloce/layer/__init__.py
veloce/layer/activation.py
veloce/layer/core.py
veloce/layer/interaction.py
veloce/model/__init__.py
veloce/model/ctr/__init__.py
veloce/model/ctr/base.py
veloce/model/ctr/deepfm.py
veloce/model/ctr/fm.py
veloce/model/ctr/fnn.py
veloce/model/ctr/lr.py
veloce/model/ctr/pnn.py
veloce/model/ctr/wdl.py
veloce/optimizer/__init__.py
veloce/optimizer/ftrl.py
veloce/optimizer/stack.py
veloce/util/__init__.py
veloce/util/benchmark_loader.py
veloce/util/common.py