Metadata-Version: 2.1
Name: veloce
Version: 0.0.1rc2
Summary: Veloce: An instant distributed computing library based on Ray stack
Home-page: https://github.com/ryantd/veloce
Author: Xiaoyu Zhai
Author-email: xiaoyu.zhai@hotmail.com
License: UNKNOWN
Platform: UNKNOWN
Requires-Python: >=3.7.1
License-File: LICENSE
